CODE_OF_CONDUCT.md
CONTRIBUTING.rst
LICENSE.txt
MANIFEST.in
README.rst
setup.cfg
setup.py
versioneer.py
docs/Makefile
docs/conf.py
docs/contributing.rst
docs/index.rst
docs/install.rst
docs/make.bat
docs/user_guide.rst
docs/api/index.rst
gmeterpy/__init__.py
gmeterpy/_version.py
gmeterpy/constants.py
gmeterpy/units.py
gmeterpy.egg-info/PKG-INFO
gmeterpy.egg-info/SOURCES.txt
gmeterpy.egg-info/dependency_links.txt
gmeterpy.egg-info/not-zip-safe
gmeterpy.egg-info/requires.txt
gmeterpy.egg-info/top_level.txt
gmeterpy/corrections/__init__.py
gmeterpy/corrections/atmosphere.py
gmeterpy/corrections/polar_motion.py
gmeterpy/corrections/tests/__init__.py
gmeterpy/corrections/tests/test_atmosphere.py
gmeterpy/corrections/tests/test_polar_motion.py
gmeterpy/corrections/tests/data/atmospheric_pressure_correction.txt