Metadata-Version: 1.1
Name: gmeterpy
Version: 0.0.2
Summary: Processing gravity measurements with Python
Home-page: https://github.com/opengrav/gmeterpy
Author: Ilya Oshchepkov
Author-email: ilya@geod.ru
License: MIT license
Keywords: geodesy,gravimetry,geophysics
Platform: UNKNOWN
Classifier: Development Status :: 1 - Planning
Classifier: Intended Audience :: Developers
Classifier: Intended Audience :: Science/Research
Classifier: License :: OSI Approved :: MIT License
Classifier: Natural Language :: English
Classifier: Programming Language :: Python :: 3
Classifier: Programming Language :: Python :: 3.5
Classifier: Programming Language :: Python :: 3.6
Classifier: Programming Language :: Python :: 3.7
Classifier: Topic :: Scientific/Engineering
